animalssay/__init__.py
animalssay/animals.py
animalssay-0.2.1.dist-info/licenses/LICENSE
animalssay-0.2.1.dist-info/METADATA
animalssay-0.2.1.dist-info/WHEEL
animalssay-0.2.1.dist-info/top_level.txt
animalssay-0.2.1.dist-info/RECORD
