Metadata-Version: 2.4
Name: animalssay
Version: 0.2.1
Summary: A simple example Python library where animals can say words
Author: hunter
License-File: LICENSE
Dynamic: author
Dynamic: description
Dynamic: description-content-type
Dynamic: license-file
Dynamic: summary
